kathir_bloom_filter-0.1.1.dist-info/METADATA
kathir_bloom_filter-0.1.1.dist-info/WHEEL
kathir_bloom_filter.pyi
kathir_bloom_filter/__init__.py
kathir_bloom_filter/__init__.pyi
kathir_bloom_filter/kathir_bloom_filter.cpython-310-x86_64-linux-gnu.so
kathir_bloom_filter/py.typed
kathir_bloom_filter-0.1.1.dist-info/RECORD
