Metadata-Version: 2.4
Name: kathir-bloom-filter
Version: 0.1.1
Classifier: Programming Language :: Rust
Classifier: Programming Language :: Python :: Implementation :: CPython
Classifier: Programming Language :: Python :: Implementation :: PyPy
Summary: Bloom filter library implemented in Rust with Python bindings
Author-email: Kathir Meyyappan <kathirmeyn@gmail.com>
License: MIT
Requires-Python: >=3.7
Project-URL: Homepage, https://github.com/kathirmeyyappan/bloom-filter
